{
  "metaData" : {
    "id" : "swiftconf_2019_implementing-pseudokeywords-through-functional-programming",
    "conference" : {
      "metaData" : {
        "id" : "swiftconf",
        "name" : "SwiftConf"
      },
      "edition" : {
        "year" : 2019
      }
    },
    "source" : {
      "type" : "youtube",
      "value" : "jWGzK-0l3w4"
    },
    "name" : "Implementing pseudo-keywords through functional programming",
    "authors" : [
      {
        "id" : "vincent-pradeilles",
        "name" : "Vincent Pradeilles"
      }
    ],
    "createdAt" : 1580734268.1973062
  },
  "description" : ""
}