[
  {
    "id" : "wiebe-elsinga",
    "name" : "Wiebe Elsinga"
  },
  {
    "id" : "Jason van der Merwe",
    "name" : "Jason van der Merwe"
  },
  {
    "id" : "Angela Guzman",
    "name" : "Angela Guzman"
  },
  {
    "id" : "Eli Ganim",
    "name" : "Eli Ganim"
  },
  {
    "id" : "Gopal Sharma",
    "name" : "Gopal Sharma"
  },
  {
    "id" : "Maria Neumayer",
    "name" : "Maria Neumayer"
  },
  {
    "id" : "Roy Marmelstein",
    "name" : "Roy Marmelstein"
  },
  {
    "id" : "clemens-morris",
    "name" : "Clemens Morris"
  },
  {
    "id" : "omkar-pimple",
    "name" : "Omkar Pimple"
  },
  {
    "id" : "luky-primadani",
    "name" : "Luky Primadani"
  },
  {
    "id" : "shem-magnezi",
    "name" : "Shem Magnezi"
  },
  {
    "id" : "daniel-steinberg",
    "name" : "Daniel Steinberg"
  },
  {
    "id" : "karolina-miekina",
    "name" : "Karolina Miekina"
  },
  {
    "id" : "matthew-eng",
    "name" : "Matthew Eng"
  },
  {
    "id" : "dan-abdinoor",
    "name" : "Dan Abdinoor"
  },
  {
    "id" : "ana-oarga",
    "name" : "Ana Oarga"
  },
  {
    "id" : "raz-burciu",
    "name" : "Raz Burciu"
  },
  {
    "id" : "john-sundell",
    "name" : "John Sundell"
  },
  {
    "id" : "felix-krause",
    "name" : "Felix Krause"
  },
  {
    "id" : "roy-marmelstein",
    "name" : "Roy Marmelstein"
  },
  {
    "id" : "meghan-kane",
    "name" : "Meghan Kane"
  },
  {
    "id" : "paul-hudson",
    "name" : "Paul Hudson"
  },
  {
    "id" : "david-hart",
    "name" : "David Hart"
  },
  {
    "id" : "adrian-kosmaczewski",
    "name" : "Adrian Kosmaczewski"
  },
  {
    "id" : "alexsander-akers",
    "name" : "Alexsander Akers"
  },
  {
    "id" : "sebastian-schmidt",
    "name" : "Sebastian Schmidt"
  },
  {
    "id" : "tobias-due-munk",
    "name" : "Tobias Due Munk"
  },
  {
    "id" : "matthias-tretter",
    "name" : "Matthias Tretter"
  },
  {
    "id" : "andreas-schlosser",
    "name" : "Andreas Schlosser"
  },
  {
    "id" : "vikram-kriplaney",
    "name" : "Vikram Kriplaney"
  },
  {
    "id" : "graham-lee",
    "name" : "Graham Lee"
  },
  {
    "id" : "dave-delong",
    "name" : "Dave DeLong"
  },
  {
    "id" : "krzysztof-zablocki",
    "name" : "Krzysztof Zablocki"
  },
  {
    "id" : "harlan-haskins",
    "name" : "Harlan Haskins"
  },
  {
    "id" : "phillip-shoemaker",
    "name" : "Phillip Shoemaker"
  },
  {
    "id" : "carola-nitz",
    "name" : "Carola Nitz"
  },
  {
    "id" : "kristaps-grinbergs",
    "name" : "Kristaps Grinbergs"
  },
  {
    "id" : "aleksandar-vacic",
    "name" : "Aleksandar Vacić"
  },
  {
    "id" : "brandon-williams",
    "name" : "Brandon Williams"
  },
  {
    "id" : "guilherme-rambo",
    "name" : "Guilherme Rambo"
  },
  {
    "id" : "marco-zimmermann",
    "name" : "Marco Zimmermann"
  },
  {
    "id" : "lara-martin",
    "name" : "Lara Martin"
  },
  {
    "id" : "janina-kutyn",
    "name" : "Janina Kutyn"
  },
  {
    "id" : "cecilia-humlelu",
    "name" : "Cecilia Humlelu"
  },
  {
    "id" : "marcin-krzyzanowski",
    "name" : "Marcin Krzyzanowski"
  },
  {
    "id" : "jonas-schmid",
    "name" : "Jonas Schmid"
  },
  {
    "id" : "soroush-khanlou",
    "name" : "Soroush Khanlou"
  },
  {
    "id" : "daniel-jalkut",
    "name" : "Daniel Jalkut"
  },
  {
    "id" : "johannes-weiss",
    "name" : "Johannes Weiss"
  },
  {
    "id" : "vincent-pradeilles",
    "name" : "Vincent Pradeilles"
  },
  {
    "id" : "tom-doron",
    "name" : "Tom Doron"
  },
  {
    "id" : "jan-kaltoun",
    "name" : "Jan Kaltoun"
  },
  {
    "id" : "lea-marolt-sonnenschein",
    "name" : "Lea Marolt Sonnenschein"
  },
  {
    "id" : "charles-parnot",
    "name" : "Charles Parnot"
  },
  {
    "id" : "mark-dalrymple",
    "name" : "Mark Dalrymple"
  },
  {
    "id" : "chris-eidhof",
    "name" : "Chris Eidhof"
  },
  {
    "id" : "nick-lockwood",
    "name" : "Nick Lockwood"
  },
  {
    "id" : "yoichi-tagaya",
    "name" : "Yoichi Tagaya"
  },
  {
    "id" : "sam-giddins",
    "name" : "Sam Giddins"
  },
  {
    "id" : "dave-verwer",
    "name" : "Dave Verwer"
  },
  {
    "id" : "max-howell",
    "name" : "Max Howell"
  },
  {
    "id" : "dimitri-dupuis-latour",
    "name" : "Dimitri Dupuis-Latour"
  },
  {
    "id" : "jeffrey-macko",
    "name" : "Jeffrey Macko"
  },
  {
    "id" : "kateryna-gridina",
    "name" : "Kateryna Gridina"
  },
  {
    "id" : "mattt",
    "name" : "Mattt"
  },
  {
    "id" : "florent-pillet",
    "name" : "Florent Pillet"
  },
  {
    "id" : "pim-stolk",
    "name" : "Pim Stolk"
  },
  {
    "id" : "vincent-leroux",
    "name" : "Vincent Leroux"
  },
  {
    "id" : "andy-bennett",
    "name" : "Andy Bennett"
  },
  {
    "id" : "mathieu-hausherr",
    "name" : "Mathieu Hausherr"
  },
  {
    "id" : "jean-christophe-pastant",
    "name" : "Jean-Christophe Pastant"
  },
  {
    "id" : "cory-benfield",
    "name" : "Cory Benfield"
  },
  {
    "id" : "ellen-shapiro",
    "name" : "Ellen Shapiro"
  },
  {
    "id" : "kilo-loco",
    "name" : "Kilo Loco"
  },
  {
    "id" : "kelly-hutchison",
    "name" : "Kelly Hutchison"
  },
  {
    "id" : "sally-shepard",
    "name" : "Sally Shepard"
  },
  {
    "id" : "james-thomson",
    "name" : "James Thomson"
  },
  {
    "id" : "esteban-torres",
    "name" : "Esteban Torres"
  },
  {
    "id" : "Yasuhiro Inami",
    "name" : "Yasuhiro Inami"
  },
  {
    "id" : "jeffrey-bergier",
    "name" : "Jeffrey Bergier"
  },
  {
    "id" : "Oscar Swanros",
    "name" : "Oscar Swanros"
  },
  {
    "id" : "Heng Hong Lee",
    "name" : "Heng Hong Lee"
  },
  {
    "id" : "mischa-hildebrand",
    "name" : "Mischa Hildebrand"
  },
  {
    "id" : "agnes-vasarhelyi",
    "name" : "Agnes Vasarhelyi"
  },
  {
    "id" : "Steven Hepting",
    "name" : "Steven Hepting"
  },
  {
    "id" : "kenneth-poon",
    "name" : "Kenneth Poon"
  },
  {
    "id" : "Omer Iqbal",
    "name" : "Omer Iqbal"
  },
  {
    "id" : "sasmito-adibowo",
    "name" : "Sasmito Adibowo"
  },
  {
    "id" : "Christian Grail",
    "name" : "Christian Grail"
  },
  {
    "id" : "sam_davies",
    "name" : "Sam Davies"
  },
  {
    "id" : "rob_napier",
    "name" : "Rob Napier"
  },
  {
    "id" : "oleg_kohtenko",
    "name" : "Oleg Kohtenko"
  },
  {
    "id" : "bruno_muniz",
    "name" : "Bruno Muniz"
  },
  {
    "id" : "dmitry_mikhailov",
    "name" : "Dmitry Mikhailov"
  },
  {
    "id" : "berta-devant",
    "name" : "Berta Devant"
  },
  {
    "id" : "inigo-mato-ruiz",
    "name" : "Inigo Mato Ruiz"
  },
  {
    "id" : "declan-mcKenna",
    "name" : "Declan McKenna"
  },
  {
    "id" : "alexander-shalamov",
    "name" : "Alexander Shalamov"
  },
  {
    "id" : "novall-khan",
    "name" : "Novall Khan"
  },
  {
    "id" : "david-collado",
    "name" : "David Collado"
  },
  {
    "id" : "josh-garnham",
    "name" : "Josh Garnham"
  },
  {
    "id" : "eleni-papanikolopoul",
    "name" : "Eleni Papanikolopoul"
  },
  {
    "id" : "dominik-scherm",
    "name" : "Dominik Scherm"
  },
  {
    "id" : "aleksandra-komagorkina",
    "name" : "Aleksandra Komagorkina"
  },
  {
    "id" : "daniel-kennett",
    "name" : "Daniel Kennett"
  },
  {
    "id" : "jp-simard",
    "name" : "JP Simard"
  },
  {
    "id" : "anastasiia-vixentael",
    "name" : "Anastasiia Vixentael"
  },
  {
    "id" : "antoine-van-der-lee",
    "name" : "Antoine van der Lee"
  },
  {
    "id" : "vadim-drobinin",
    "name" : "Vadim Drobinin"
  },
  {
    "id" : "elviro-rocca",
    "name" : "Elviro Rocca"
  },
  {
    "id" : "marco-de-nittis",
    "name" : "Marco De Nittis"
  },
  {
    "id" : "daniel-leivers",
    "name" : "Daniel Leivers"
  },
  {
    "id" : "tomas-camin",
    "name" : "Tomas Camin"
  },
  {
    "id" : "francesco-bigagnoli",
    "name" : "Francesco Bigagnoli"
  },
  {
    "id" : "tim-condon",
    "name" : "Tim Condon"
  },
  {
    "id" : "stefano-mondino",
    "name" : "Stefano Mondino"
  },
  {
    "id" : "manuel-carrasco-molina",
    "name" : "Manuel Carrasco Molina"
  },
  {
    "id" : "michael-flarup",
    "name" : "Michael Flarup"
  },
  {
    "id" : "calogero-sanfilippo",
    "name" : "Calogero Sanfilippo"
  },
  {
    "id" : "rikke-koblauch",
    "name" : "Rikke Koblauch"
  },
  {
    "id" : "gopal-sharma",
    "name" : "Gopal Sharma"
  },
  {
    "id" : "tim-oliver",
    "name" : "Tim Oliver"
  },
  {
    "id" : "abhishek-pandey",
    "name" : "Abhishek Pandey"
  },
  {
    "id" : "noah-gilmore",
    "name" : "Noah Gilmore"
  },
  {
    "id" : "amruta-itagi",
    "name" : "Amruta Itagi"
  },
  {
    "id" : "matthew-delves",
    "name" : "Matthew Delves"
  },
  {
    "id" : "Bharath Nagaraj Rao",
    "name" : "Bharath Nagaraj Rao"
  },
  {
    "id" : "ritesh-gupta",
    "name" : "Ritesh Gupta"
  },
  {
    "id" : "daiki-matsudate",
    "name" : "Daiki Matsudate"
  },
  {
    "id" : "sowndharya-maheswaran",
    "name" : "Sowndharya Maheswaran"
  },
  {
    "id" : "srikanth-kv",
    "name" : "Srikanth KV"
  },
  {
    "id" : "tim-mitra",
    "name" : "Tim Mitra"
  },
  {
    "id" : "abbey-jackson",
    "name" : "Abbey Jackson"
  },
  {
    "id" : "chris-ching",
    "name" : "Chris Ching"
  },
  {
    "id" : "veronica-ray",
    "name" : "Veronica Ray"
  },
  {
    "id" : "Leo Dion",
    "name" : "Leo Dion"
  },
  {
    "id" : "rohan-trivedi",
    "name" : "Rohan Trivedi"
  },
  {
    "id" : "charles-joseph",
    "name" : "Charles Joseph"
  },
  {
    "id" : "marwan-alani",
    "name" : "Marwan Alani"
  },
  {
    "id" : "lyle-resnick",
    "name" : "Lyle Resnick"
  },
  {
    "id" : "frank-courville",
    "name" : "Frank Courville"
  },
  {
    "id" : "kyle-newsome",
    "name" : "Kyle Newsome"
  },
  {
    "id" : "audrey-tam",
    "name" : "Audrey Tam"
  },
  {
    "id" : "logan-wright",
    "name" : "Logan Wright"
  },
  {
    "id" : "jon-tait-beason",
    "name" : "Jon-Tait Beason"
  },
  {
    "id" : "christina-moulton",
    "name" : "Christina Moulton"
  },
  {
    "id" : "peter-steinberger",
    "name" : "Peter Steinberger"
  },
  {
    "id" : "april-wensel",
    "name" : "April Wensel"
  },
  {
    "id" : "kentaro-matsumae",
    "name" : "Kentaro Matsumae"
  },
  {
    "id" : "kaya-thomas",
    "name" : "Kaya Thomas"
  },
  {
    "id" : "tom-harrington",
    "name" : "Tom Harrington"
  },
  {
    "id" : "jen-person",
    "name" : "Jen Person"
  },
  {
    "id" : "leah-culver",
    "name" : "Leah Culver"
  },
  {
    "id" : "Mattt",
    "name" : "Mattt"
  },
  {
    "id" : "erica-correa",
    "name" : "Erica Correa"
  },
  {
    "id" : "bas-broek",
    "name" : "Bas Broek"
  },
  {
    "id" : "sebastiaan-de-with",
    "name" : "Sebastiaan de With"
  },
  {
    "id" : "alicia-v-carr",
    "name" : "Alicia V Carr"
  },
  {
    "id" : "chris-bailey",
    "name" : "Chris Bailey"
  },
  {
    "id" : "ian-partridge",
    "name" : "Ian Partridge"
  },
  {
    "id" : "Tom Doron",
    "name" : "Tom Doron"
  },
  {
    "id" : "michael_ilseman",
    "name" : "Michael Ilseman"
  },
  {
    "id" : "david_okun",
    "name" : "David Okun"
  },
  {
    "id" : "ian_partridge",
    "name" : "Ian Partridge"
  },
  {
    "id" : "yuto_mizutani",
    "name" : "Yuto Mizutani"
  },
  {
    "id" : "kristina-fox",
    "name" : "Kristina Fox"
  },
  {
    "id" : "yuta-saito",
    "name" : "Yuta Saito"
  },
  {
    "id" : "donny-wals",
    "name" : "Donny Wals"
  },
  {
    "id" : "andrew-madsen",
    "name" : "Andrew Madsen"
  },
  {
    "id" : "yusuke-hosonuma",
    "name" : "Yusuke Hosonuma"
  },
  {
    "id" : "adam-bell",
    "name" : "Adam Bell"
  },
  {
    "id" : "rina-kotake",
    "name" : "Rina Kotake"
  },
  {
    "id" : "yusuke-kita",
    "name" : "Yusuke Kita"
  },
  {
    "id" : "kishikawa-katsumi",
    "name" : "Kishikawa Katsumi"
  },
  {
    "id" : "Kamil Borzym",
    "name" : "Kamil Borzym"
  },
  {
    "id" : "ryo-izumi",
    "name" : "Ryo Izumi"
  },
  {
    "id" : "maxim-cramer",
    "name" : "Maxim Cramer"
  },
  {
    "id" : "nic-laughter",
    "name" : "Nic Laughter"
  },
  {
    "id" : "nobuo-saito",
    "name" : "Nobuo Saito"
  },
  {
    "id" : "namrata-bandekar",
    "name" : "Namrata Bandekar"
  },
  {
    "id" : "michael-petrie",
    "name" : "Michael Petrie"
  },
  {
    "id" : "liz-marley",
    "name" : "Liz Marley"
  },
  {
    "id" : "yuki-aki",
    "name" : "Yuki Aki"
  },
  {
    "id" : "benedikt-terhechte",
    "name" : "Benedikt Terhechte"
  },
  {
    "id" : "tomoya-hirano",
    "name" : "Tomoya Hirano"
  },
  {
    "id" : "hikaru-yoshimura",
    "name" : "Hikaru Yoshimura"
  },
  {
    "id" : "alaina-kafkes",
    "name" : "Alaina Kafkes"
  },
  {
    "id" : "glenna-buford",
    "name" : "Glenna Buford"
  },
  {
    "id" : "julia-roggatz",
    "name" : "Julia Roggatz"
  },
  {
    "id" : "kate-castellano",
    "name" : "Kate Castellano"
  },
  {
    "id" : "nataliya-patsovska",
    "name" : "Nataliya Patsovska"
  },
  {
    "id" : "füsun-wehrmann",
    "name" : "Füsun Wehrmann"
  },
  {
    "id" : "neha-kulkarni",
    "name" : "Neha Kulkarni"
  },
  {
    "id" : "anne-cahalan",
    "name" : "Anne Cahalan"
  },
  {
    "id" : "ellie-shin",
    "name" : "Ellie Shin"
  },
  {
    "id" : "julie-yaunches",
    "name" : "Julie Yaunches"
  },
  {
    "id" : "lea-marolt",
    "name" : "Lea Marolt"
  },
  {
    "id" : "shannon-hughes",
    "name" : "Shannon Hughes"
  },
  {
    "id" : "lisa-dziuba",
    "name" : "Lisa Dziuba"
  },
  {
    "id" : "apple",
    "name" : "Apple"
  }
]